Nevow-0.14.5.data/data/doc/Makefile
Nevow-0.14.5.data/data/doc/conf.py
Nevow-0.14.5.data/data/doc/index.rst
Nevow-0.14.5.data/data/doc/_static/.hidden
Nevow-0.14.5.data/data/doc/_templates/.hidden
Nevow-0.14.5.data/data/doc/howto/deployment.rst
Nevow-0.14.5.data/data/doc/howto/gettingstarted.rst
Nevow-0.14.5.data/data/doc/howto/glossary.rst
Nevow-0.14.5.data/data/doc/howto/intro.rst
Nevow-0.14.5.data/data/doc/howto/publishing.rst
Nevow-0.14.5.data/data/doc/howto/traversal.rst
Nevow-0.14.5.data/data/doc/howto/xmltemplates.rst
Nevow-0.14.5.data/data/doc/howto/chattutorial/concepts.rst
Nevow-0.14.5.data/data/doc/howto/chattutorial/env.rst
Nevow-0.14.5.data/data/doc/howto/chattutorial/index.rst
Nevow-0.14.5.data/data/doc/howto/chattutorial/intro.rst
Nevow-0.14.5.data/data/doc/howto/chattutorial/part00/index.rst
Nevow-0.14.5.data/data/doc/howto/chattutorial/part00/listings/echothing/__init__.py
Nevow-0.14.5.data/data/doc/howto/chattutorial/part00/listings/echothing/echobox.py
Nevow-0.14.5.data/data/doc/howto/chattutorial/part00/listings/echothing/template.html
Nevow-0.14.5.data/data/doc/howto/chattutorial/part00/listings/echothing/js/EchoThing.js
Nevow-0.14.5.data/data/doc/howto/chattutorial/part00/listings/nevow/plugins/echothing_package.py
Nevow-0.14.5.data/data/doc/howto/chattutorial/part01/index.rst
Nevow-0.14.5.data/data/doc/howto/chattutorial/part01/listings/chatthing/__init__.py
Nevow-0.14.5.data/data/doc/howto/chattutorial/part01/listings/chatthing/chatterbox.py
Nevow-0.14.5.data/data/doc/howto/chattutorial/part01/listings/chatthing/template.html
Nevow-0.14.5.data/data/doc/howto/chattutorial/part01/listings/chatthing/js/ChatThing.js
Nevow-0.14.5.data/data/doc/howto/chattutorial/part01/listings/nevow/plugins/chatthing_package.py
Nevow-0.14.5.data/data/doc/howto/listings/gettingstarted/helloworld.py
Nevow-0.14.5.data/data/doc/howto/listings/gettingstarted/helloworld.tac
Nevow-0.14.5.data/data/doc/man/nevow-xmlgettext.1
Nevow-0.14.5.data/data/doc/old/nevow.doc
Nevow-0.14.5.dist-info/LICENSE
Nevow-0.14.5.dist-info/METADATA
Nevow-0.14.5.dist-info/WHEEL
Nevow-0.14.5.dist-info/top_level.txt
Nevow-0.14.5.dist-info/RECORD
