Metadata-Version: 2.1
Name: Nevow
Version: 0.14.5
Summary: Web Application Construction Kit
Home-page: https://github.com/twisted/nevow
Author: Divmod, Inc.
Author-email: support@divmod.org
Maintainer: Twisted Matrix Labs
Maintainer-email: twisted-web@twistedmatrix.com
License: MIT
Platform: any
Classifier: Development Status :: 5 - Production/Stable
Classifier: Framework :: Twisted
Classifier: Intended Audience :: Developers
Classifier: License :: OSI Approved :: MIT License
Classifier: Programming Language :: Python
Classifier: Topic :: Internet :: WWW/HTTP :: Dynamic Content
Classifier: Topic :: Software Development :: Libraries
Requires-Dist: twisted (>=16.3)
Provides-Extra: doc
Requires-Dist: Sphinx ; extra == 'doc'
